nb_path/__init__.py
nb_path/nb_path_class.py
nb_path/nb_path_py_impoter.py
nb_path-2.5.dist-info/METADATA
nb_path-2.5.dist-info/WHEEL
nb_path-2.5.dist-info/top_level.txt
nb_path-2.5.dist-info/RECORD
