Metadata-Version: 2.4
Name: nb-path
Version: 2.5
Summary: A Python path library that gives filesystem operations superpowers
Home-page: https://github.com/ydf0509/nb_path
Author: ydf0509
Author-email: ydf0509@example.com
Classifier: Development Status :: 5 - Production/Stable
Classifier: Programming Language :: Python :: 3
Classifier: Operating System :: OS Independent
Classifier: Topic :: Software Development :: Libraries :: Python Modules
Classifier: Intended Audience :: Developers
Requires-Python: >=3.6
Provides-Extra: download
Requires-Dist: requests; extra == "download"
Requires-Dist: tqdm; extra == "download"
Provides-Extra: lock
Requires-Dist: filelock; extra == "lock"
Provides-Extra: all
Requires-Dist: requests; extra == "all"
Requires-Dist: tqdm; extra == "all"
Requires-Dist: filelock; extra == "all"
Dynamic: author
Dynamic: author-email
Dynamic: classifier
Dynamic: description
Dynamic: description-content-type
Dynamic: home-page
Dynamic: provides-extra
Dynamic: requires-python
Dynamic: summary
